adafruit_ssd1306.py
adafruit_circuitpython_ssd1306-2.12.20.dist-info/licenses/LICENSE
adafruit_circuitpython_ssd1306-2.12.20.dist-info/METADATA
adafruit_circuitpython_ssd1306-2.12.20.dist-info/WHEEL
adafruit_circuitpython_ssd1306-2.12.20.dist-info/top_level.txt
adafruit_circuitpython_ssd1306-2.12.20.dist-info/RECORD
